crc16/__init__.py
crc16/crc16pure.py
crc16/test.py
ThaiQR-1.0.1.dist-info/METADATA
ThaiQR-1.0.1.dist-info/WHEEL
ThaiQR-1.0.1.dist-info/top_level.txt
ThaiQR-1.0.1.dist-info/RECORD
