Metadata-Version: 2.1
Name: ThaiQR
Version: 1.0.1
Summary: Thai QR Python library
Author: Psskynyrd
Author-email: pasupong.seelalek@gmail.com
